testwater/__init__.py
testwater/common.py
testwater/testwater.py
testwater-0.0.1.dist-info/LICENSE
testwater-0.0.1.dist-info/METADATA
testwater-0.0.1.dist-info/WHEEL
testwater-0.0.1.dist-info/entry_points.txt
testwater-0.0.1.dist-info/top_level.txt
testwater-0.0.1.dist-info/RECORD
